pathogen_decision_engine/__init__.py
pathogen_decision_engine/decision_engine_cli.py
pathogen_decision_engine/pathogen_decision_engine.py
pathogen_decision_engine-1.3.1.dist-info/LICENSE
pathogen_decision_engine-1.3.1.dist-info/METADATA
pathogen_decision_engine-1.3.1.dist-info/WHEEL
pathogen_decision_engine-1.3.1.dist-info/entry_points.txt
pathogen_decision_engine-1.3.1.dist-info/top_level.txt
pathogen_decision_engine-1.3.1.dist-info/RECORD
