Metadata-Version: 2.1
Name: pathogen-decision-engine
Version: 1.3.1
License-File: LICENSE
Requires-Dist: pandas >=2.0.3
Requires-Dist: rule-engine
